stretched-0.0.1.dist-info/METADATA
stretched-0.0.1.dist-info/WHEEL
stretched/.DS_Store
stretched/style.py
stretched/_stretch.py
stretched/layout.py
stretched/__init__.py
stretched/node.py
stretched/stretched.cpython-35m-darwin.so
stretched-0.0.1.dist-info/RECORD
