Metadata-Version: 2.1
Name: stretched
Version: 0.0.1
Summary: Python bindings for Stretch (High performance flexbox implementation written in rust.)
Author: Nathan Michlo <NathanJMichlo@gmail.com>
Author-Email: Nathan Michlo <NathanJMichlo@gmail.com>
Maintainer: Nathan Michlo
Maintainer-Email: NathanJMichlo@gmail.com
License: MIT
